{
  "ms": [
    {
      "ts": "2016-03-29T00:15:00.000Z",
      "v": 0.12099
    },
    {
      "ts": "2016-03-29T00:30:00.000Z",
      "v": 0.11833
    },
    {
      "ts": "2016-03-29T00:45:00.000Z",
      "v": 0.11614
    },
    {
      "ts": "2016-03-29T01:00:00.000Z",
      "v": 0.11472
    },
    {
      "ts": "2016-03-29T01:15:00.000Z",
      "v": 0.11315
    },
    {
      "ts": "2016-03-29T01:30:00.000Z",
      "v": 0.11195
    },
    {
      "ts": "2016-03-29T01:45:00.000Z",
      "v": 0.11091
    },
    {
      "ts": "2016-03-29T02:00:00.000Z",
      "v": 0.11008
    },
    {
      "ts": "2016-03-29T02:15:00.000Z",
      "v": 0.10962
    },
    {
      "ts": "2016-03-29T02:30:00.000Z",
      "v": 0.10988
    },
    {
      "ts": "2016-03-29T02:45:00.000Z",
      "v": 0.11068
    },
    {
      "ts": "2016-03-29T03:00:00.000Z",
      "v": 0.11213
    },
    {
      "ts": "2016-03-29T03:15:00.000Z",
      "v": 0.11441
    },
    {
      "ts": "2016-03-29T03:30:00.000Z",
      "v": 0.11819
    },
    {
      "ts": "2016-03-29T03:45:00.000Z",
      "v": 0.12301
    },
    {
      "ts": "2016-03-29T04:00:00.000Z",
      "v": 0.13221
    },
    {
      "ts": "2016-03-29T04:15:00.000Z",
      "v": 0.14148
    },
    {
      "ts": "2016-03-29T04:30:00.000Z",
      "v": 0.15259
    },
    {
      "ts": "2016-03-29T04:45:00.000Z",
      "v": 0.16587
    },
    {
      "ts": "2016-03-29T05:00:00.000Z",
      "v": 0.18633
    },
    {
      "ts": "2016-03-29T05:15:00.000Z",
      "v": 0.19357
    },
    {
      "ts": "2016-03-29T05:30:00.000Z",
      "v": 0.20026
    },
    {
      "ts": "2016-03-29T05:45:00.000Z",
      "v": 0.20467
    },
    {
      "ts": "2016-03-29T06:00:00.000Z",
      "v": 0.20773
    },
    {
      "ts": "2016-03-29T06:15:00.000Z",
      "v": 0.2078
    },
    {
      "ts": "2016-03-29T06:30:00.000Z",
      "v": 0.21191
    },
    {
      "ts": "2016-03-29T06:45:00.000Z",
      "v": 0.21741
    },
    {
      "ts": "2016-03-29T07:00:00.000Z",
      "v": 0.2222
    },
    {
      "ts": "2016-03-29T07:15:00.000Z",
      "v": 0.22653
    },
    {
      "ts": "2016-03-29T07:30:00.000Z",
      "v": 0.22694
    },
    {
      "ts": "2016-03-29T07:45:00.000Z",
      "v": 0.22652
    },
    {
      "ts": "2016-03-29T08:00:00.000Z",
      "v": 0.22326
    },
    {
      "ts": "2016-03-29T08:15:00.000Z",
      "v": 0.22408
    },
    {
      "ts": "2016-03-29T08:30:00.000Z",
      "v": 0.22298
    },
    {
      "ts": "2016-03-29T08:45:00.000Z",
      "v": 0.22195
    },
    {
      "ts": "2016-03-29T09:00:00.000Z",
      "v": 0.21973
    },
    {
      "ts": "2016-03-29T09:15:00.000Z",
      "v": 0.2189
    },
    {
      "ts": "2016-03-29T09:30:00.000Z",
      "v": 0.22044
    },
    {
      "ts": "2016-03-29T09:45:00.000Z",
      "v": 0.2205
    },
    {
      "ts": "2016-03-29T10:00:00.000Z",
      "v": 0.22172
    },
    {
      "ts": "2016-03-29T10:15:00.000Z",
      "v": 0.22117
    },
    {
      "ts": "2016-03-29T10:30:00.000Z",
      "v": 0.21779
    },
    {
      "ts": "2016-03-29T10:45:00.000Z",
      "v": 0.21646
    },
    {
      "ts": "2016-03-29T11:00:00.000Z",
      "v": 0.21487
    },
    {
      "ts": "2016-03-29T11:15:00.000Z",
      "v": 0.21445
    },
    {
      "ts": "2016-03-29T11:30:00.000Z",
      "v": 0.21625
    },
    {
      "ts": "2016-03-29T11:45:00.000Z",
      "v": 0.21347
    },
    {
      "ts": "2016-03-29T12:00:00.000Z",
      "v": 0.21373
    },
    {
      "ts": "2016-03-29T12:15:00.000Z",
      "v": 0.2099
    },
    {
      "ts": "2016-03-29T12:30:00.000Z",
      "v": 0.21007
    },
    {
      "ts": "2016-03-29T12:45:00.000Z",
      "v": 0.20857
    },
    {
      "ts": "2016-03-29T13:00:00.000Z",
      "v": 0.20489
    },
    {
      "ts": "2016-03-29T13:15:00.000Z",
      "v": 0.20397
    },
    {
      "ts": "2016-03-29T13:30:00.000Z",
      "v": 0.20648
    },
    {
      "ts": "2016-03-29T13:45:00.000Z",
      "v": 0.20827
    },
    {
      "ts": "2016-03-29T14:00:00.000Z",
      "v": 0.21325
    },
    {
      "ts": "2016-03-29T14:15:00.000Z",
      "v": 0.22037
    },
    {
      "ts": "2016-03-29T14:30:00.000Z",
      "v": 0.22917
    },
    {
      "ts": "2016-03-29T14:45:00.000Z",
      "v": 0.24335
    },
    {
      "ts": "2016-03-29T15:00:00.000Z",
      "v": 0.25407
    },
    {
      "ts": "2016-03-29T15:15:00.000Z",
      "v": 0.26417
    },
    {
      "ts": "2016-03-29T15:30:00.000Z",
      "v": 0.26943
    },
    {
      "ts": "2016-03-29T15:45:00.000Z",
      "v": 0.27637
    },
    {
      "ts": "2016-03-29T16:00:00.000Z",
      "v": 0.27344
    },
    {
      "ts": "2016-03-29T16:15:00.000Z",
      "v": 0.27428
    },
    {
      "ts": "2016-03-29T16:30:00.000Z",
      "v": 0.27564
    },
    {
      "ts": "2016-03-29T16:45:00.000Z",
      "v": 0.27805
    },
    {
      "ts": "2016-03-29T17:00:00.000Z",
      "v": 0.28503
    },
    {
      "ts": "2016-03-29T17:15:00.000Z",
      "v": 0.29041
    },
    {
      "ts": "2016-03-29T17:30:00.000Z",
      "v": 0.29364
    },
    {
      "ts": "2016-03-29T17:45:00.000Z",
      "v": 0.29892
    },
    {
      "ts": "2016-03-29T18:00:00.000Z",
      "v": 0.30334
    },
    {
      "ts": "2016-03-29T18:15:00.000Z",
      "v": 0.30864
    },
    {
      "ts": "2016-03-29T18:30:00.000Z",
      "v": 0.31096
    },
    {
      "ts": "2016-03-29T18:45:00.000Z",
      "v": 0.31288
    },
    {
      "ts": "2016-03-29T19:00:00.000Z",
      "v": 0.30832
    },
    {
      "ts": "2016-03-29T19:15:00.000Z",
      "v": 0.30499
    },
    {
      "ts": "2016-03-29T19:30:00.000Z",
      "v": 0.29798
    },
    {
      "ts": "2016-03-29T19:45:00.000Z",
      "v": 0.29179
    },
    {
      "ts": "2016-03-29T20:00:00.000Z",
      "v": 0.28224
    },
    {
      "ts": "2016-03-29T20:15:00.000Z",
      "v": 0.27345
    },
    {
      "ts": "2016-03-29T20:30:00.000Z",
      "v": 0.26469
    },
    {
      "ts": "2016-03-29T20:45:00.000Z",
      "v": 0.25469
    }
  ]
}